fretboardgtr/__init__.py
fretboardgtr/_version.py
fretboardgtr/base.py
fretboardgtr/constants.py
fretboardgtr/exporters.py
fretboardgtr/fretboard.py
fretboardgtr/note_colors.py
fretboardgtr/notes.py
fretboardgtr/notes_creators.py
fretboardgtr/utils.py
fretboardgtr/elements/__init__.py
fretboardgtr/elements/background.py
fretboardgtr/elements/base.py
fretboardgtr/elements/cross.py
fretboardgtr/elements/fret_number.py
fretboardgtr/elements/frets.py
fretboardgtr/elements/neck_dots.py
fretboardgtr/elements/notes.py
fretboardgtr/elements/nut.py
fretboardgtr/elements/strings.py
fretboardgtr/elements/tuning.py
fretboardgtr/fretboards/__init__.py
fretboardgtr/fretboards/base.py
fretboardgtr/fretboards/config.py
fretboardgtr/fretboards/converters.py
fretboardgtr/fretboards/elements.py
fretboardgtr/fretboards/horizontal.py
fretboardgtr/fretboards/vertical.py
fretboardgtr-0.2.7.dist-info/LICENSE
fretboardgtr-0.2.7.dist-info/METADATA
fretboardgtr-0.2.7.dist-info/WHEEL
fretboardgtr-0.2.7.dist-info/top_level.txt
fretboardgtr-0.2.7.dist-info/RECORD
