Metadata-Version: 2.1
Name: fretboardgtr
Version: 0.2.7
Summary: Package that make easy creation of fretboards and chords diagrams
Author-email: Antoine Gibek <antoine.gibek@gmail.com>
License: GNU AFFERO GENERAL PUBLIC LICENSE
Project-URL: homepage, https://github.com/antscloud/fretboardgtr
Project-URL: documentation, https://fretboardgtr.readthedocs.io/en/latest
Project-URL: repository, https://github.com/antscloud/fretboardgtr
Project-URL: changelog, https://github.com/antscloud/fretboardgtr/blob/main/CHANGELOG.md
Project-URL: Bug Tracker, https://github.com/antscloud/fretboardgtr/issues
Keywords: fretboardgtr,fretboard,chord,guitar,bass
Classifier: Development Status :: 2 - Pre-Alpha
Classifier: Intended Audience :: Developers
Classifier: License :: OSI Approved :: GNU Affero General Public License v3
Classifier: Natural Language :: English
Classifier: Programming Language :: Python :: Implementation :: CPython
Classifier: Programming Language :: Python :: 3
Classifier: Programming Language :: Python :: 3.8
Classifier: Programming Language :: Python :: 3.9
Classifier: Programming Language :: Python :: 3.10
Classifier: Programming Language :: Python :: 3.11
Requires-Python: >=3.8
License-File: LICENSE
Requires-Dist: reportlab <=4
Requires-Dist: svglib
Requires-Dist: svgwrite
Requires-Dist: pypdf
Provides-Extra: dev
Requires-Dist: fretboardgtr ; extra == 'dev'
Requires-Dist: pytest >=6.1.1 ; extra == 'dev'
Requires-Dist: pytest-cov >=2.10.1 ; extra == 'dev'
Requires-Dist: pytest-mock >=3.6.1 ; extra == 'dev'
Requires-Dist: coverage >=5.3 ; extra == 'dev'
Requires-Dist: sphinx >=4.5.0 ; extra == 'dev'
Requires-Dist: myst ; extra == 'dev'
Requires-Dist: myst-parser ; extra == 'dev'
Requires-Dist: sphinx-book-theme >=0.3.0 ; extra == 'dev'
Requires-Dist: pre-commit ; extra == 'dev'
Requires-Dist: black ; extra == 'dev'
Requires-Dist: flake8 ; extra == 'dev'
Requires-Dist: mypy ; extra == 'dev'
Requires-Dist: six ; extra == 'dev'
Requires-Dist: pypdf ; extra == 'dev'
